README.md
setup.cfg
setup.py
src/celtic_lib/__init__.py
src/celtic_lib/celtic_lib.py
src/celtic_lib.egg-info/PKG-INFO
src/celtic_lib.egg-info/SOURCES.txt
src/celtic_lib.egg-info/dependency_links.txt
src/celtic_lib.egg-info/requires.txt
src/celtic_lib.egg-info/top_level.txt
src/celtic_lib.egg-info/zip-safe