Metadata-Version: 1.1
Name: celtic-lib
Version: 0.0.7
Summary: A python library for wrapping around the CELTIC service
Home-page: UNKNOWN
Author: eLIPSE
Author-email: UNKNOWN
License: MIT License
Platform: UNKNOWN
Classifier: Programming Language :: Python :: 2
Classifier: Programming Language :: Python :: 2.7
Classifier: Programming Language :: Python :: 3
Classifier: Programming Language :: Python :: 3.5
Classifier: Programming Language :: Python :: 3.6
